[
  {
    "day": 17,
    "both": 14642,
    "first": 10037
  },
  {
    "day": 16,
    "both": 20925,
    "first": 5226
  },
  {
    "day": 15,
    "both": 26634,
    "first": 8784
  },
  {
    "day": 14,
    "both": 36577,
    "first": 4144
  },
  {
    "day": 13,
    "both": 38735,
    "first": 4812
  },
  {
    "day": 12,
    "both": 37326,
    "first": 10380
  },
  {
    "day": 11,
    "both": 50826,
    "first": 8272
  },
  {
    "day": 10,
    "both": 55657,
    "first": 1187
  },
  {
    "day": 9,
    "both": 54473,
    "first": 10643
  },
  {
    "day": 8,
    "both": 64740,
    "first": 2699
  },
  {
    "day": 7,
    "both": 75041,
    "first": 3897
  },
  {
    "day": 6,
    "both": 71721,
    "first": 24583
  },
  {
    "day": 5,
    "both": 96383,
    "first": 12329
  },
  {
    "day": 4,
    "both": 117162,
    "first": 9986
  },
  {
    "day": 3,
    "both": 145598,
    "first": 15734
  },
  {
    "day": 2,
    "both": 160633,
    "first": 39270
  },
  {
    "day": 1,
    "both": 225926,
    "first": 16248
  }
]